portainer/__init__.py
portainer-0.1b0.dist-info/METADATA
portainer-0.1b0.dist-info/RECORD
portainer-0.1b0.dist-info/WHEEL
portainer-0.1b0.dist-info/top_level.txt
