Metadata-Version: 2.1
Name: portainer
Version: 0.1b0
Summary: Python module to interact with the Portainer API
Home-page: https://github.com/rnt/python-portainer
Author: Renato Covarrubias
Author-email: rnt@rnt.cl
License: UNKNOWN
Download-URL: https://github.com/rnt/python-portainer/archive/0.1.tar.gz
Keywords: portainer
Platform: UNKNOWN
Requires-Dist: requests
